marisol/__init__.py
marisol/marisol.py
Marisol-0.3.0.dist-info/zip-safe
Marisol-0.3.0.dist-info/top_level.txt
Marisol-0.3.0.dist-info/METADATA
Marisol-0.3.0.dist-info/DESCRIPTION.rst
Marisol-0.3.0.dist-info/metadata.json
Marisol-0.3.0.dist-info/WHEEL
Marisol-0.3.0.dist-info/RECORD
